concurrent_ssh-0.3.1.data/scripts/cssh
cssh/__init__.py
cssh/_version.py
cssh/cli.py
cssh/executor.py
cssh/io.py
cssh/signal_handler.py
concurrent_ssh-0.3.1.dist-info/LICENSE
concurrent_ssh-0.3.1.dist-info/METADATA
concurrent_ssh-0.3.1.dist-info/WHEEL
concurrent_ssh-0.3.1.dist-info/top_level.txt
concurrent_ssh-0.3.1.dist-info/RECORD
