Metadata-Version: 2.1
Name: concurrent-ssh
Version: 0.3.1
Summary: Executing commands using SSH concurrently on multiple hosts
Home-page: https://github.com/DCsunset/concurrent-ssh
Author: DCsunset
Author-email: DCsunset@protonmail.com
License: AGPL-3.0
Classifier: Environment :: Console
Classifier: Topic :: System :: Networking
Classifier: Topic :: Software Development :: Libraries
Classifier: Intended Audience :: Developers
Classifier: Programming Language :: Python
Classifier: License :: OSI Approved :: GNU Affero General Public License v3
Requires-Python: >=3.9
License-File: LICENSE
Requires-Dist: aiostream
Requires-Dist: rich
